pixkit/__init__.py
pixkit/pixel.pyd
pixkit/pixel.pyi
pixkit-0.0.1.dist-info/licenses/LICENSE
pixkit-0.0.1.dist-info/METADATA
pixkit-0.0.1.dist-info/WHEEL
pixkit-0.0.1.dist-info/top_level.txt
pixkit-0.0.1.dist-info/RECORD
